LICENSE
MANIFEST.in
README.rst
setup.cfg
setup.py
gapic_google_cloud_error_reporting_v1beta1.egg-info/PKG-INFO
gapic_google_cloud_error_reporting_v1beta1.egg-info/SOURCES.txt
gapic_google_cloud_error_reporting_v1beta1.egg-info/dependency_links.txt
gapic_google_cloud_error_reporting_v1beta1.egg-info/namespace_packages.txt
gapic_google_cloud_error_reporting_v1beta1.egg-info/requires.txt
gapic_google_cloud_error_reporting_v1beta1.egg-info/top_level.txt
google/__init__.py
google/__init__.pyc
google/cloud/__init__.py
google/cloud/__init__.pyc
google/cloud/gapic/__init__.py
google/cloud/gapic/__init__.pyc
google/cloud/gapic/errorreporting/__init__.py
google/cloud/gapic/errorreporting/v1beta1/__init__.py
google/cloud/gapic/errorreporting/v1beta1/enums.py
google/cloud/gapic/errorreporting/v1beta1/error_group_service_api.py
google/cloud/gapic/errorreporting/v1beta1/error_group_service_client_config.json
google/cloud/gapic/errorreporting/v1beta1/error_stats_service_api.py
google/cloud/gapic/errorreporting/v1beta1/error_stats_service_client_config.json
google/cloud/gapic/errorreporting/v1beta1/report_errors_service_api.py
google/cloud/gapic/errorreporting/v1beta1/report_errors_service_client_config.json